{
  "descriptionHash": "08A3F65E62ECD45C122E47D32465A1B88836BF509683813F6C2E4F0AA150C7B1CE942FE8AD3C6861212573AFB17A7157630F941CFAFD67F04D0A580CE86D6986",
  "descriptionLocation": "https://api.twitter.com/2/openapi.json",
  "lockFileVersion": "1.0.0",
  "kiotaVersion": "1.30.0",
  "clientClassName": "XClient",
  "typeAccessModifier": "Public",
  "clientNamespaceName": "XbyOpenApi.Core.Client",
  "language": "CSharp",
  "usesBackingStore": false,
  "excludeBackwardCompatible": true,
  "includeAdditionalData": true,
  "disableSSLValidation": false,
  "serializers": [
    "Microsoft.Kiota.Serialization.Json.JsonSerializationWriterFactory",
    "Microsoft.Kiota.Serialization.Text.TextSerializationWriterFactory",
    "Microsoft.Kiota.Serialization.Form.FormSerializationWriterFactory",
    "Microsoft.Kiota.Serialization.Multipart.MultipartSerializationWriterFactory"
  ],
  "deserializers": [
    "Microsoft.Kiota.Serialization.Json.JsonParseNodeFactory",
    "Microsoft.Kiota.Serialization.Text.TextParseNodeFactory",
    "Microsoft.Kiota.Serialization.Form.FormParseNodeFactory"
  ],
  "structuredMimeTypes": [
    "application/json",
    "text/plain;q=0.9",
    "application/x-www-form-urlencoded;q=0.2",
    "multipart/form-data;q=0.1"
  ],
  "includePatterns": [],
  "excludePatterns": [],
  "disabledValidationRules": []
}